pubmed_download/__init__.py
pubmed_download/pubmed_download.py
pubmed_download/pubmed_mapper.py
pubmed_download-0.2.1.dist-info/METADATA
pubmed_download-0.2.1.dist-info/RECORD
pubmed_download-0.2.1.dist-info/WHEEL
pubmed_download-0.2.1.dist-info/top_level.txt
