Metadata-Version: 2.1
Name: pubmed-download
Version: 0.2.1
Summary: download pdf by pmid
Home-page: https://github.com/decouples/pubmed_download
Author: lin.li
Author-email: lilinxr@gmail.com
License: UNKNOWN
Platform: UNKNOWN
Classifier: Programming Language :: Python :: 3
Classifier: License :: OSI Approved :: MIT License
Classifier: Operating System :: OS Independent
Requires-Dist: setuptools
Requires-Dist: pandas
Requires-Dist: lxml
Requires-Dist: requests
Requires-Dist: PyPDF2
Requires-Dist: bs4
